sketchup_mcp/__init__.py
sketchup_mcp/__main__.py
sketchup_mcp/server.py
sketchup_mcp-0.1.17.dist-info/METADATA
sketchup_mcp-0.1.17.dist-info/WHEEL
sketchup_mcp-0.1.17.dist-info/entry_points.txt
sketchup_mcp-0.1.17.dist-info/top_level.txt
sketchup_mcp-0.1.17.dist-info/RECORD
