Metadata-Version: 2.2
Name: sketchup-mcp
Version: 0.1.17
Summary: Sketchup integration through Model Context Protocol
Author-email: Your Name <your.email@example.com>
License: MIT
Project-URL: Homepage, https://github.com/yourusername/sketchup-mcp
Project-URL: Issues, https://github.com/yourusername/sketchup-mcp/issues
Classifier: Programming Language :: Python :: 3
Classifier: License :: OSI Approved :: MIT License
Classifier: Operating System :: OS Independent
Requires-Python: >=3.10
Requires-Dist: mcp[cli]>=1.3.0
